pyklang/kompile.py
pyklang/bindings.cpython-312-darwin.so
pyklang/__init__.py
pyklang/bindings.pyi
pyklang/py.typed
pyklang-0.2.0.dist-info/RECORD
pyklang-0.2.0.dist-info/WHEEL
pyklang-0.2.0.dist-info/entry_points.txt
pyklang-0.2.0.dist-info/top_level.txt
pyklang-0.2.0.dist-info/METADATA
