Metadata-Version: 2.1
Name: pyklang
Version: 0.2.0
Summary: Python interface for Klang
Home-page: https://github.com/kscalelabs/klang
Author: K-Scale Labs
Requires-Python: >=3.11
Requires-Dist: click
Provides-Extra: dev
Requires-Dist: black; extra == "dev"
Requires-Dist: darglint; extra == "dev"
Requires-Dist: mypy; extra == "dev"
Requires-Dist: pytest; extra == "dev"
Requires-Dist: ruff; extra == "dev"
